[
 {
  "date": "2026-06-18",
  "matchup": "Toronto Blue Jays @ Boston Red Sox",
  "prob_home": 0.7015,
  "predicted": "Boston Red Sox",
  "winner": "Toronto Blue Jays",
  "score": "4\u20133",
  "correct": false
 },
 {
  "date": "2026-06-18",
  "matchup": "Cleveland Guardians @ Milwaukee Brewers",
  "prob_home": 0.574,
  "predicted": "Milwaukee Brewers",
  "winner": "Cleveland Guardians",
  "score": "4\u20132",
  "correct": false
 },
 {
  "date": "2026-06-18",
  "matchup": "Minnesota Twins @ Texas Rangers",
  "prob_home": 0.6006,
  "predicted": "Texas Rangers",
  "winner": "Minnesota Twins",
  "score": "9\u20133",
  "correct": false
 },
 {
  "date": "2026-06-18",
  "matchup": "Baltimore Orioles @ Seattle Mariners",
  "prob_home": 0.5443,
  "predicted": "Seattle Mariners",
  "winner": "Seattle Mariners",
  "score": "0\u20133",
  "correct": true
 },
 {
  "date": "2026-06-18",
  "matchup": "New York Mets @ Philadelphia Phillies",
  "prob_home": 0.5126,
  "predicted": "Philadelphia Phillies",
  "winner": "New York Mets",
  "score": "6\u20134",
  "correct": false
 },
 {
  "date": "2026-06-18",
  "matchup": "Chicago White Sox @ New York Yankees",
  "prob_home": 0.3454,
  "predicted": "Chicago White Sox",
  "winner": "Chicago White Sox",
  "score": "5\u20131",
  "correct": true
 },
 {
  "date": "2026-06-18",
  "matchup": "St. Louis Cardinals @ Kansas City Royals",
  "prob_home": 0.4901,
  "predicted": "St. Louis Cardinals",
  "winner": "Kansas City Royals",
  "score": "6\u201314",
  "correct": false
 },
 {
  "date": "2026-06-18",
  "matchup": "Los Angeles Angels @ Athletics",
  "prob_home": 0.5717,
  "predicted": "Athletics",
  "winner": "Athletics",
  "score": "0\u20135",
  "correct": true
 },
 {
  "date": "2026-06-19",
  "matchup": "Toronto Blue Jays @ Chicago Cubs",
  "prob_home": 0.6105,
  "predicted": "Chicago Cubs",
  "winner": "Chicago Cubs",
  "score": "2\u201316",
  "correct": true
 },
 {
  "date": "2026-06-19",
  "matchup": "Chicago White Sox @ Detroit Tigers",
  "prob_home": 0.585,
  "predicted": "Detroit Tigers",
  "winner": "Detroit Tigers",
  "score": "3\u20134",
  "correct": true
 },
 {
  "date": "2026-06-19",
  "matchup": "Cincinnati Reds @ New York Yankees",
  "prob_home": 0.6671,
  "predicted": "New York Yankees",
  "winner": "New York Yankees",
  "score": "0\u20135",
  "correct": true
 },
 {
  "date": "2026-06-19",
  "matchup": "Washington Nationals @ Tampa Bay Rays",
  "prob_home": 0.5835,
  "predicted": "Tampa Bay Rays",
  "winner": "Tampa Bay Rays",
  "score": "2\u20135",
  "correct": true
 },
 {
  "date": "2026-06-19",
  "matchup": "San Francisco Giants @ Miami Marlins",
  "prob_home": 0.5915,
  "predicted": "Miami Marlins",
  "winner": "Miami Marlins",
  "score": "3\u20134",
  "correct": true
 },
 {
  "date": "2026-06-19",
  "matchup": "Milwaukee Brewers @ Atlanta Braves",
  "prob_home": 0.6323,
  "predicted": "Atlanta Braves",
  "winner": "Atlanta Braves",
  "score": "2\u20133",
  "correct": true
 },
 {
  "date": "2026-06-19",
  "matchup": "San Diego Padres @ Texas Rangers",
  "prob_home": 0.6984,
  "predicted": "Texas Rangers",
  "winner": "Texas Rangers",
  "score": "7\u20139",
  "correct": true
 },
 {
  "date": "2026-06-19",
  "matchup": "Cleveland Guardians @ Houston Astros",
  "prob_home": 0.3754,
  "predicted": "Cleveland Guardians",
  "winner": "Houston Astros",
  "score": "3\u20139",
  "correct": false
 },
 {
  "date": "2026-06-19",
  "matchup": "St. Louis Cardinals @ Kansas City Royals",
  "prob_home": 0.3644,
  "predicted": "St. Louis Cardinals",
  "winner": "Kansas City Royals",
  "score": "5\u20136",
  "correct": false
 },
 {
  "date": "2026-06-19",
  "matchup": "Pittsburgh Pirates @ Colorado Rockies",
  "prob_home": 0.4604,
  "predicted": "Pittsburgh Pirates",
  "winner": "Colorado Rockies",
  "score": "3\u20134",
  "correct": false
 },
 {
  "date": "2026-06-19",
  "matchup": "Los Angeles Angels @ Athletics",
  "prob_home": 0.5889,
  "predicted": "Athletics",
  "winner": "Athletics",
  "score": "11\u201312",
  "correct": true
 },
 {
  "date": "2026-06-19",
  "matchup": "Minnesota Twins @ Arizona Diamondbacks",
  "prob_home": 0.9143,
  "predicted": "Arizona Diamondbacks",
  "winner": "Arizona Diamondbacks",
  "score": "5\u20139",
  "correct": true
 },
 {
  "date": "2026-06-19",
  "matchup": "Baltimore Orioles @ Los Angeles Dodgers",
  "prob_home": 0.5903,
  "predicted": "Los Angeles Dodgers",
  "winner": "Los Angeles Dodgers",
  "score": "5\u20136",
  "correct": true
 },
 {
  "date": "2026-06-19",
  "matchup": "Boston Red Sox @ Seattle Mariners",
  "prob_home": 0.5943,
  "predicted": "Seattle Mariners",
  "winner": "Boston Red Sox",
  "score": "6\u20132",
  "correct": false
 },
 {
  "date": "2026-06-20",
  "matchup": "Chicago White Sox @ Detroit Tigers",
  "prob_home": 0.615,
  "predicted": "Detroit Tigers",
  "winner": "Detroit Tigers",
  "score": "1\u20134",
  "correct": true
 },
 {
  "date": "2026-06-20",
  "matchup": "Cincinnati Reds @ New York Yankees",
  "prob_home": 0.6227,
  "predicted": "New York Yankees",
  "winner": "Cincinnati Reds",
  "score": "10\u20132",
  "correct": false
 },
 {
  "date": "2026-06-20",
  "matchup": "Toronto Blue Jays @ Chicago Cubs",
  "prob_home": 0.541,
  "predicted": "Chicago Cubs",
  "winner": "Toronto Blue Jays",
  "score": "8\u20136",
  "correct": false
 },
 {
  "date": "2026-06-20",
  "matchup": "San Diego Padres @ Texas Rangers",
  "prob_home": 0.5303,
  "predicted": "Texas Rangers",
  "winner": "San Diego Padres",
  "score": "6\u20134",
  "correct": false
 },
 {
  "date": "2026-06-20",
  "matchup": "Washington Nationals @ Tampa Bay Rays",
  "prob_home": 0.5551,
  "predicted": "Tampa Bay Rays",
  "winner": "Washington Nationals",
  "score": "4\u20133",
  "correct": false
 },
 {
  "date": "2026-06-20",
  "matchup": "San Francisco Giants @ Miami Marlins",
  "prob_home": 0.5866,
  "predicted": "Miami Marlins",
  "winner": "Miami Marlins",
  "score": "3\u20136",
  "correct": true
 },
 {
  "date": "2026-06-20",
  "matchup": "Milwaukee Brewers @ Atlanta Braves",
  "prob_home": 0.6927,
  "predicted": "Atlanta Braves",
  "winner": "Atlanta Braves",
  "score": "3\u20134",
  "correct": true
 },
 {
  "date": "2026-06-20",
  "matchup": "Cleveland Guardians @ Houston Astros",
  "prob_home": 0.5653,
  "predicted": "Houston Astros",
  "winner": "Cleveland Guardians",
  "score": "8\u20131",
  "correct": false
 },
 {
  "date": "2026-06-20",
  "matchup": "New York Mets @ Philadelphia Phillies",
  "prob_home": 0.6043,
  "predicted": "Philadelphia Phillies",
  "winner": "Philadelphia Phillies",
  "score": "3\u201315",
  "correct": true
 },
 {
  "date": "2026-06-20",
  "matchup": "Pittsburgh Pirates @ Colorado Rockies",
  "prob_home": 0.1235,
  "predicted": "Pittsburgh Pirates",
  "winner": "Colorado Rockies",
  "score": "1\u20132",
  "correct": false
 },
 {
  "date": "2026-06-20",
  "matchup": "Los Angeles Angels @ Athletics",
  "prob_home": 0.5765,
  "predicted": "Athletics",
  "winner": "Los Angeles Angels",
  "score": "7\u20130",
  "correct": false
 },
 {
  "date": "2026-06-20",
  "matchup": "Baltimore Orioles @ Los Angeles Dodgers",
  "prob_home": 0.7178,
  "predicted": "Los Angeles Dodgers",
  "winner": "Baltimore Orioles",
  "score": "3\u20132",
  "correct": false
 },
 {
  "date": "2026-06-20",
  "matchup": "Boston Red Sox @ Seattle Mariners",
  "prob_home": 0.5866,
  "predicted": "Seattle Mariners",
  "winner": "Boston Red Sox",
  "score": "5\u20131",
  "correct": false
 },
 {
  "date": "2026-06-20",
  "matchup": "Minnesota Twins @ Arizona Diamondbacks",
  "prob_home": 0.4977,
  "predicted": "Minnesota Twins",
  "winner": "Minnesota Twins",
  "score": "16\u20138",
  "correct": true
 },
 {
  "date": "2026-06-21",
  "matchup": "Cincinnati Reds @ New York Yankees",
  "prob_home": 0.5052,
  "predicted": "New York Yankees",
  "winner": "Cincinnati Reds",
  "score": "4\u20131",
  "correct": false
 },
 {
  "date": "2026-06-21",
  "matchup": "Milwaukee Brewers @ Atlanta Braves",
  "prob_home": 0.6782,
  "predicted": "Atlanta Braves",
  "winner": "Milwaukee Brewers",
  "score": "9\u20134",
  "correct": false
 },
 {
  "date": "2026-06-21",
  "matchup": "Washington Nationals @ Tampa Bay Rays",
  "prob_home": 0.5351,
  "predicted": "Tampa Bay Rays",
  "winner": "Tampa Bay Rays",
  "score": "3\u20134",
  "correct": true
 },
 {
  "date": "2026-06-21",
  "matchup": "Chicago White Sox @ Detroit Tigers",
  "prob_home": 0.8219,
  "predicted": "Detroit Tigers",
  "winner": "Detroit Tigers",
  "score": "4\u20135",
  "correct": true
 },
 {
  "date": "2026-06-21",
  "matchup": "San Francisco Giants @ Miami Marlins",
  "prob_home": 0.3978,
  "predicted": "San Francisco Giants",
  "winner": "Miami Marlins",
  "score": "1\u20132",
  "correct": false
 },
 {
  "date": "2026-06-21",
  "matchup": "Cleveland Guardians @ Houston Astros",
  "prob_home": 0.3714,
  "predicted": "Cleveland Guardians",
  "winner": "Houston Astros",
  "score": "1\u20132",
  "correct": false
 },
 {
  "date": "2026-06-21",
  "matchup": "St. Louis Cardinals @ Kansas City Royals",
  "prob_home": 0.5718,
  "predicted": "Kansas City Royals",
  "winner": "St. Louis Cardinals",
  "score": "12\u201310",
  "correct": false
 },
 {
  "date": "2026-06-21",
  "matchup": "San Diego Padres @ Texas Rangers",
  "prob_home": 0.3714,
  "predicted": "San Diego Padres",
  "winner": "Texas Rangers",
  "score": "3\u20134",
  "correct": false
 },
 {
  "date": "2026-06-21",
  "matchup": "Pittsburgh Pirates @ Colorado Rockies",
  "prob_home": 0.3975,
  "predicted": "Pittsburgh Pirates",
  "winner": "Pittsburgh Pirates",
  "score": "8\u20136",
  "correct": true
 },
 {
  "date": "2026-06-21",
  "matchup": "Minnesota Twins @ Arizona Diamondbacks",
  "prob_home": 0.527,
  "predicted": "Arizona Diamondbacks",
  "winner": "Minnesota Twins",
  "score": "4\u20132",
  "correct": false
 },
 {
  "date": "2026-06-21",
  "matchup": "Los Angeles Angels @ Athletics",
  "prob_home": 0.4645,
  "predicted": "Los Angeles Angels",
  "winner": "Los Angeles Angels",
  "score": "9\u20137",
  "correct": true
 },
 {
  "date": "2026-06-21",
  "matchup": "Baltimore Orioles @ Los Angeles Dodgers",
  "prob_home": 0.485,
  "predicted": "Baltimore Orioles",
  "winner": "Baltimore Orioles",
  "score": "12\u20131",
  "correct": true
 },
 {
  "date": "2026-06-21",
  "matchup": "Boston Red Sox @ Seattle Mariners",
  "prob_home": 0.5532,
  "predicted": "Seattle Mariners",
  "winner": "Seattle Mariners",
  "score": "1\u20133",
  "correct": true
 },
 {
  "date": "2026-06-21",
  "matchup": "New York Mets @ Philadelphia Phillies",
  "prob_home": 0.8592,
  "predicted": "Philadelphia Phillies",
  "winner": "Philadelphia Phillies",
  "score": "2\u20136",
  "correct": true
 },
 {
  "date": "2026-06-22",
  "matchup": "New York Yankees @ Detroit Tigers",
  "prob_home": 0.2167,
  "predicted": "New York Yankees",
  "winner": "Detroit Tigers",
  "score": "3\u20135",
  "correct": false
 },
 {
  "date": "2026-06-22",
  "matchup": "Kansas City Royals @ Tampa Bay Rays",
  "prob_home": 0.9583,
  "predicted": "Tampa Bay Rays",
  "winner": "Kansas City Royals",
  "score": "2\u20131",
  "correct": false
 },
 {
  "date": "2026-06-22",
  "matchup": "Texas Rangers @ Miami Marlins",
  "prob_home": 0.4347,
  "predicted": "Texas Rangers",
  "winner": "Texas Rangers",
  "score": "4\u20133",
  "correct": true
 },
 {
  "date": "2026-06-22",
  "matchup": "Philadelphia Phillies @ Washington Nationals",
  "prob_home": 0.5168,
  "predicted": "Washington Nationals",
  "winner": "Washington Nationals",
  "score": "1\u20134",
  "correct": true
 },
 {
  "date": "2026-06-22",
  "matchup": "Houston Astros @ Toronto Blue Jays",
  "prob_home": 0.6022,
  "predicted": "Toronto Blue Jays",
  "winner": "Toronto Blue Jays",
  "score": "2\u20134",
  "correct": true
 },
 {
  "date": "2026-06-22",
  "matchup": "Milwaukee Brewers @ Cincinnati Reds",
  "prob_home": 0.4607,
  "predicted": "Milwaukee Brewers",
  "winner": "Milwaukee Brewers",
  "score": "2\u20131",
  "correct": true
 },
 {
  "date": "2026-06-22",
  "matchup": "Los Angeles Dodgers @ Minnesota Twins",
  "prob_home": 0.4491,
  "predicted": "Los Angeles Dodgers",
  "winner": "Los Angeles Dodgers",
  "score": "2\u20131",
  "correct": true
 },
 {
  "date": "2026-06-22",
  "matchup": "Cleveland Guardians @ Chicago White Sox",
  "prob_home": 0.4934,
  "predicted": "Cleveland Guardians",
  "winner": "Chicago White Sox",
  "score": "5\u20136",
  "correct": false
 },
 {
  "date": "2026-06-22",
  "matchup": "Arizona Diamondbacks @ St. Louis Cardinals",
  "prob_home": 0.5709,
  "predicted": "St. Louis Cardinals",
  "winner": "St. Louis Cardinals",
  "score": "2\u20133",
  "correct": true
 },
 {
  "date": "2026-06-22",
  "matchup": "Boston Red Sox @ Colorado Rockies",
  "prob_home": 0.5585,
  "predicted": "Colorado Rockies",
  "winner": "Colorado Rockies",
  "score": "2\u20133",
  "correct": true
 },
 {
  "date": "2026-06-22",
  "matchup": "Baltimore Orioles @ Los Angeles Angels",
  "prob_home": 0.5021,
  "predicted": "Los Angeles Angels",
  "winner": "Baltimore Orioles",
  "score": "6\u20131",
  "correct": false
 },
 {
  "date": "2026-06-22",
  "matchup": "Atlanta Braves @ San Diego Padres",
  "prob_home": 0.4697,
  "predicted": "Atlanta Braves",
  "winner": "San Diego Padres",
  "score": "0\u20131",
  "correct": false
 },
 {
  "date": "2026-06-25",
  "matchup": "Athletics @ San Francisco Giants",
  "prob_home": 0.65,
  "predicted": "San Francisco Giants",
  "winner": "Athletics",
  "score": "9\u20136",
  "correct": false
 },
 {
  "date": "2026-06-25",
  "matchup": "Houston Astros @ Detroit Tigers",
  "prob_home": 0.5527,
  "predicted": "Detroit Tigers",
  "winner": "Houston Astros",
  "score": "2\u20131",
  "correct": false
 },
 {
  "date": "2026-06-25",
  "matchup": "Philadelphia Phillies @ Washington Nationals",
  "prob_home": 0.5369,
  "predicted": "Washington Nationals",
  "winner": "Philadelphia Phillies",
  "score": "10\u20135",
  "correct": false
 },
 {
  "date": "2026-06-25",
  "matchup": "Texas Rangers @ Toronto Blue Jays",
  "prob_home": 0.4291,
  "predicted": "Texas Rangers",
  "winner": "Texas Rangers",
  "score": "6\u20135",
  "correct": true
 },
 {
  "date": "2026-06-25",
  "matchup": "Chicago Cubs @ New York Mets",
  "prob_home": 0.4331,
  "predicted": "Chicago Cubs",
  "winner": "Chicago Cubs",
  "score": "4\u20133",
  "correct": true
 },
 {
  "date": "2026-06-25",
  "matchup": "New York Yankees @ Boston Red Sox",
  "prob_home": 0.2891,
  "predicted": "New York Yankees",
  "winner": "Boston Red Sox",
  "score": "3\u20136",
  "correct": false
 },
 {
  "date": "2026-06-26",
  "matchup": "Houston Astros @ Detroit Tigers",
  "prob_home": 0.6815,
  "predicted": "Detroit Tigers",
  "winner": "Detroit Tigers",
  "score": "0\u20138",
  "correct": true
 },
 {
  "date": "2026-06-26",
  "matchup": "Cincinnati Reds @ Pittsburgh Pirates",
  "prob_home": 0.5323,
  "predicted": "Pittsburgh Pirates",
  "winner": "Cincinnati Reds",
  "score": "6\u20134",
  "correct": false
 },
 {
  "date": "2026-06-26",
  "matchup": "Washington Nationals @ Baltimore Orioles",
  "prob_home": 0.3952,
  "predicted": "Washington Nationals",
  "winner": "Baltimore Orioles",
  "score": "1\u20133",
  "correct": false
 },
 {
  "date": "2026-06-26",
  "matchup": "Texas Rangers @ Toronto Blue Jays",
  "prob_home": 0.5672,
  "predicted": "Toronto Blue Jays",
  "winner": "Texas Rangers",
  "score": "5\u20134",
  "correct": false
 },
 {
  "date": "2026-06-26",
  "matchup": "Seattle Mariners @ Cleveland Guardians",
  "prob_home": 0.4994,
  "predicted": "Seattle Mariners",
  "winner": "Seattle Mariners",
  "score": "3\u20131",
  "correct": true
 },
 {
  "date": "2026-06-26",
  "matchup": "Arizona Diamondbacks @ Tampa Bay Rays",
  "prob_home": 0.5212,
  "predicted": "Tampa Bay Rays",
  "winner": "Tampa Bay Rays",
  "score": "1\u20136",
  "correct": true
 },
 {
  "date": "2026-06-26",
  "matchup": "Philadelphia Phillies @ New York Mets",
  "prob_home": 0.393,
  "predicted": "Philadelphia Phillies",
  "winner": "Philadelphia Phillies",
  "score": "2\u20131",
  "correct": true
 },
 {
  "date": "2026-06-26",
  "matchup": "New York Yankees @ Boston Red Sox",
  "prob_home": 0.4233,
  "predicted": "New York Yankees",
  "winner": "Boston Red Sox",
  "score": "1\u20136",
  "correct": false
 },
 {
  "date": "2026-06-26",
  "matchup": "Kansas City Royals @ Chicago White Sox",
  "prob_home": 0.6318,
  "predicted": "Chicago White Sox",
  "winner": "Chicago White Sox",
  "score": "1\u201322",
  "correct": true
 },
 {
  "date": "2026-06-26",
  "matchup": "Chicago Cubs @ Milwaukee Brewers",
  "prob_home": 0.8082,
  "predicted": "Milwaukee Brewers",
  "winner": "Milwaukee Brewers",
  "score": "2\u20136",
  "correct": true
 },
 {
  "date": "2026-06-26",
  "matchup": "Colorado Rockies @ Minnesota Twins",
  "prob_home": 0.5714,
  "predicted": "Minnesota Twins",
  "winner": "Minnesota Twins",
  "score": "8\u20139",
  "correct": true
 },
 {
  "date": "2026-06-26",
  "matchup": "Miami Marlins @ St. Louis Cardinals",
  "prob_home": 0.5483,
  "predicted": "St. Louis Cardinals",
  "winner": "Miami Marlins",
  "score": "4\u20130",
  "correct": false
 },
 {
  "date": "2026-06-26",
  "matchup": "Athletics @ Los Angeles Angels",
  "prob_home": 0.5212,
  "predicted": "Los Angeles Angels",
  "winner": "Athletics",
  "score": "9\u20133",
  "correct": false
 },
 {
  "date": "2026-06-26",
  "matchup": "Los Angeles Dodgers @ San Diego Padres",
  "prob_home": 0.4883,
  "predicted": "Los Angeles Dodgers",
  "winner": "San Diego Padres",
  "score": "1\u20137",
  "correct": false
 },
 {
  "date": "2026-06-26",
  "matchup": "Atlanta Braves @ San Francisco Giants",
  "prob_home": 0.3948,
  "predicted": "Atlanta Braves",
  "winner": "Atlanta Braves",
  "score": "3\u20131",
  "correct": true
 },
 {
  "date": "2026-06-27",
  "matchup": "Houston Astros @ Detroit Tigers",
  "prob_home": 0.753,
  "predicted": "Detroit Tigers",
  "winner": "Houston Astros",
  "score": "8\u20136",
  "correct": false
 },
 {
  "date": "2026-06-27",
  "matchup": "Texas Rangers @ Toronto Blue Jays",
  "prob_home": 0.6259,
  "predicted": "Toronto Blue Jays",
  "winner": "Texas Rangers",
  "score": "7\u20134",
  "correct": false
 },
 {
  "date": "2026-06-27",
  "matchup": "Cincinnati Reds @ Pittsburgh Pirates",
  "prob_home": 0.5125,
  "predicted": "Pittsburgh Pirates",
  "winner": "Cincinnati Reds",
  "score": "9\u20137",
  "correct": false
 },
 {
  "date": "2026-06-27",
  "matchup": "Philadelphia Phillies @ New York Mets",
  "prob_home": 0.3998,
  "predicted": "Philadelphia Phillies",
  "winner": "New York Mets",
  "score": "2\u20136",
  "correct": false
 },
 {
  "date": "2026-06-27",
  "matchup": "Kansas City Royals @ Chicago White Sox",
  "prob_home": 0.4886,
  "predicted": "Kansas City Royals",
  "winner": "Chicago White Sox",
  "score": "1\u20132",
  "correct": false
 },
 {
  "date": "2026-06-27",
  "matchup": "Arizona Diamondbacks @ Tampa Bay Rays",
  "prob_home": 0.4322,
  "predicted": "Arizona Diamondbacks",
  "winner": "Tampa Bay Rays",
  "score": "2\u20134",
  "correct": false
 },
 {
  "date": "2026-06-27",
  "matchup": "Washington Nationals @ Baltimore Orioles",
  "prob_home": 0.4867,
  "predicted": "Washington Nationals",
  "winner": "Washington Nationals",
  "score": "4\u20133",
  "correct": true
 },
 {
  "date": "2026-06-27",
  "matchup": "Seattle Mariners @ Cleveland Guardians",
  "prob_home": 0.3335,
  "predicted": "Seattle Mariners",
  "winner": "Cleveland Guardians",
  "score": "3\u20134",
  "correct": false
 },
 {
  "date": "2026-06-27",
  "matchup": "Colorado Rockies @ Minnesota Twins",
  "prob_home": 0.797,
  "predicted": "Minnesota Twins",
  "winner": "Colorado Rockies",
  "score": "8\u20135",
  "correct": false
 },
 {
  "date": "2026-06-27",
  "matchup": "Chicago Cubs @ Milwaukee Brewers",
  "prob_home": 0.696,
  "predicted": "Milwaukee Brewers",
  "winner": "Chicago Cubs",
  "score": "8\u20132",
  "correct": false
 },
 {
  "date": "2026-06-27",
  "matchup": "Miami Marlins @ St. Louis Cardinals",
  "prob_home": 0.5712,
  "predicted": "St. Louis Cardinals",
  "winner": "Miami Marlins",
  "score": "5\u20131",
  "correct": false
 },
 {
  "date": "2026-06-27",
  "matchup": "Los Angeles Dodgers @ San Diego Padres",
  "prob_home": 0.3335,
  "predicted": "Los Angeles Dodgers",
  "winner": "Los Angeles Dodgers",
  "score": "15\u20133",
  "correct": true
 },
 {
  "date": "2026-06-27",
  "matchup": "Atlanta Braves @ San Francisco Giants",
  "prob_home": 0.6038,
  "predicted": "San Francisco Giants",
  "winner": "San Francisco Giants",
  "score": "0\u20135",
  "correct": true
 },
 {
  "date": "2026-06-27",
  "matchup": "Athletics @ Los Angeles Angels",
  "prob_home": 0.6157,
  "predicted": "Los Angeles Angels",
  "winner": "Los Angeles Angels",
  "score": "2\u20135",
  "correct": true
 },
 {
  "date": "2026-06-28",
  "matchup": "Washington Nationals @ Baltimore Orioles",
  "prob_home": 0.5963,
  "predicted": "Baltimore Orioles",
  "winner": "Washington Nationals",
  "score": "6\u20134",
  "correct": false
 },
 {
  "date": "2026-06-28",
  "matchup": "Cincinnati Reds @ Pittsburgh Pirates",
  "prob_home": 0.5139,
  "predicted": "Pittsburgh Pirates",
  "winner": "Pittsburgh Pirates",
  "score": "4\u20139",
  "correct": true
 },
 {
  "date": "2026-06-28",
  "matchup": "Texas Rangers @ Toronto Blue Jays",
  "prob_home": 0.5092,
  "predicted": "Toronto Blue Jays",
  "winner": "Texas Rangers",
  "score": "3\u20132",
  "correct": false
 },
 {
  "date": "2026-06-28",
  "matchup": "Houston Astros @ Detroit Tigers",
  "prob_home": 0.4424,
  "predicted": "Houston Astros",
  "winner": "Houston Astros",
  "score": "7\u20135",
  "correct": true
 },
 {
  "date": "2026-06-28",
  "matchup": "Seattle Mariners @ Cleveland Guardians",
  "prob_home": 0.3075,
  "predicted": "Seattle Mariners",
  "winner": "Cleveland Guardians",
  "score": "5\u20136",
  "correct": false
 },
 {
  "date": "2026-06-28",
  "matchup": "Arizona Diamondbacks @ Tampa Bay Rays",
  "prob_home": 0.6381,
  "predicted": "Tampa Bay Rays",
  "winner": "Tampa Bay Rays",
  "score": "1\u20135",
  "correct": true
 },
 {
  "date": "2026-06-28",
  "matchup": "Philadelphia Phillies @ New York Mets",
  "prob_home": 0.6736,
  "predicted": "New York Mets",
  "winner": "Philadelphia Phillies",
  "score": "5\u20134",
  "correct": false
 },
 {
  "date": "2026-06-28",
  "matchup": "Colorado Rockies @ Minnesota Twins",
  "prob_home": 0.5132,
  "predicted": "Minnesota Twins",
  "winner": "Minnesota Twins",
  "score": "2\u20133",
  "correct": true
 },
 {
  "date": "2026-06-28",
  "matchup": "Kansas City Royals @ Chicago White Sox",
  "prob_home": 0.7054,
  "predicted": "Chicago White Sox",
  "winner": "Kansas City Royals",
  "score": "5\u20134",
  "correct": false
 },
 {
  "date": "2026-06-28",
  "matchup": "Chicago Cubs @ Milwaukee Brewers",
  "prob_home": 0.608,
  "predicted": "Milwaukee Brewers",
  "winner": "Chicago Cubs",
  "score": "4\u20133",
  "correct": false
 },
 {
  "date": "2026-06-28",
  "matchup": "Miami Marlins @ St. Louis Cardinals",
  "prob_home": 0.5405,
  "predicted": "St. Louis Cardinals",
  "winner": "St. Louis Cardinals",
  "score": "1\u20132",
  "correct": true
 },
 {
  "date": "2026-06-28",
  "matchup": "Athletics @ Los Angeles Angels",
  "prob_home": 0.537,
  "predicted": "Los Angeles Angels",
  "winner": "Los Angeles Angels",
  "score": "1\u20134",
  "correct": true
 },
 {
  "date": "2026-06-28",
  "matchup": "Atlanta Braves @ San Francisco Giants",
  "prob_home": 0.4527,
  "predicted": "Atlanta Braves",
  "winner": "San Francisco Giants",
  "score": "2\u20133",
  "correct": false
 },
 {
  "date": "2026-06-28",
  "matchup": "Los Angeles Dodgers @ San Diego Padres",
  "prob_home": 0.5446,
  "predicted": "San Diego Padres",
  "winner": "Los Angeles Dodgers",
  "score": "4\u20132",
  "correct": false
 },
 {
  "date": "2026-06-28",
  "matchup": "New York Yankees @ Boston Red Sox",
  "prob_home": 0.5092,
  "predicted": "Boston Red Sox",
  "winner": "Boston Red Sox",
  "score": "4\u20135",
  "correct": true
 },
 {
  "date": "2026-06-29",
  "matchup": "Chicago White Sox @ Baltimore Orioles",
  "prob_home": 0.6376,
  "predicted": "Baltimore Orioles",
  "winner": "Chicago White Sox",
  "score": "8\u20132",
  "correct": false
 },
 {
  "date": "2026-06-29",
  "matchup": "Pittsburgh Pirates @ Philadelphia Phillies",
  "prob_home": 0.3676,
  "predicted": "Pittsburgh Pirates",
  "winner": "Pittsburgh Pirates",
  "score": "11\u20137",
  "correct": true
 },
 {
  "date": "2026-06-29",
  "matchup": "Detroit Tigers @ New York Yankees",
  "prob_home": 0.5054,
  "predicted": "New York Yankees",
  "winner": "Detroit Tigers",
  "score": "7\u20133",
  "correct": false
 },
 {
  "date": "2026-06-29",
  "matchup": "New York Mets @ Toronto Blue Jays",
  "prob_home": 0.532,
  "predicted": "Toronto Blue Jays",
  "winner": "Toronto Blue Jays",
  "score": "1\u20132",
  "correct": true
 },
 {
  "date": "2026-06-29",
  "matchup": "Washington Nationals @ Boston Red Sox",
  "prob_home": 0.5039,
  "predicted": "Boston Red Sox",
  "winner": "Boston Red Sox",
  "score": "3\u20136",
  "correct": true
 },
 {
  "date": "2026-06-29",
  "matchup": "Texas Rangers @ Cleveland Guardians",
  "prob_home": 0.6892,
  "predicted": "Cleveland Guardians",
  "winner": "Texas Rangers",
  "score": "6\u20133",
  "correct": false
 },
 {
  "date": "2026-06-29",
  "matchup": "Cincinnati Reds @ Milwaukee Brewers",
  "prob_home": 0.5098,
  "predicted": "Milwaukee Brewers",
  "winner": "Milwaukee Brewers",
  "score": "3\u20135",
  "correct": true
 },
 {
  "date": "2026-06-29",
  "matchup": "San Diego Padres @ Chicago Cubs",
  "prob_home": 0.4479,
  "predicted": "San Diego Padres",
  "winner": "Chicago Cubs",
  "score": "2\u20133",
  "correct": false
 },
 {
  "date": "2026-06-29",
  "matchup": "Minnesota Twins @ Houston Astros",
  "prob_home": 0.5546,
  "predicted": "Houston Astros",
  "winner": "Minnesota Twins",
  "score": "5\u20134",
  "correct": false
 },
 {
  "date": "2026-06-29",
  "matchup": "Miami Marlins @ Colorado Rockies",
  "prob_home": 0.3667,
  "predicted": "Miami Marlins",
  "winner": "Miami Marlins",
  "score": "10\u20137",
  "correct": true
 },
 {
  "date": "2026-06-29",
  "matchup": "Los Angeles Dodgers @ Athletics",
  "prob_home": 0.6802,
  "predicted": "Athletics",
  "winner": "Los Angeles Dodgers",
  "score": "9\u20134",
  "correct": false
 },
 {
  "date": "2026-06-29",
  "matchup": "Los Angeles Angels @ Seattle Mariners",
  "prob_home": 0.8832,
  "predicted": "Seattle Mariners",
  "winner": "Seattle Mariners",
  "score": "2\u20136",
  "correct": true
 },
 {
  "date": "2026-06-29",
  "matchup": "San Francisco Giants @ Arizona Diamondbacks",
  "prob_home": 0.5602,
  "predicted": "Arizona Diamondbacks",
  "winner": "Arizona Diamondbacks",
  "score": "4\u20135",
  "correct": true
 },
 {
  "date": "2026-06-30",
  "matchup": "Chicago White Sox @ Baltimore Orioles",
  "prob_home": 0.4571,
  "predicted": "Chicago White Sox",
  "winner": "Chicago White Sox",
  "score": "9\u20133",
  "correct": true
 },
 {
  "date": "2026-06-30",
  "matchup": "Texas Rangers @ Cleveland Guardians",
  "prob_home": 0.5614,
  "predicted": "Cleveland Guardians",
  "winner": "Texas Rangers",
  "score": "4\u20132",
  "correct": false
 },
 {
  "date": "2026-06-30",
  "matchup": "Pittsburgh Pirates @ Philadelphia Phillies",
  "prob_home": 0.6538,
  "predicted": "Philadelphia Phillies",
  "winner": "Philadelphia Phillies",
  "score": "0\u20138",
  "correct": true
 },
 {
  "date": "2026-06-30",
  "matchup": "Detroit Tigers @ New York Yankees",
  "prob_home": 0.5173,
  "predicted": "New York Yankees",
  "winner": "Detroit Tigers",
  "score": "9\u20133",
  "correct": false
 },
 {
  "date": "2026-06-30",
  "matchup": "New York Mets @ Toronto Blue Jays",
  "prob_home": 0.5415,
  "predicted": "Toronto Blue Jays",
  "winner": "New York Mets",
  "score": "3\u20130",
  "correct": false
 },
 {
  "date": "2026-06-30",
  "matchup": "Washington Nationals @ Boston Red Sox",
  "prob_home": 0.5336,
  "predicted": "Boston Red Sox",
  "winner": "Washington Nationals",
  "score": "8\u20131",
  "correct": false
 },
 {
  "date": "2026-06-30",
  "matchup": "St. Louis Cardinals @ Atlanta Braves",
  "prob_home": 0.7911,
  "predicted": "Atlanta Braves",
  "winner": "St. Louis Cardinals",
  "score": "5\u20133",
  "correct": false
 },
 {
  "date": "2026-06-30",
  "matchup": "Tampa Bay Rays @ Kansas City Royals",
  "prob_home": 0.5407,
  "predicted": "Kansas City Royals",
  "winner": "Tampa Bay Rays",
  "score": "10\u20134",
  "correct": false
 },
 {
  "date": "2026-06-30",
  "matchup": "Cincinnati Reds @ Milwaukee Brewers",
  "prob_home": 0.59,
  "predicted": "Milwaukee Brewers",
  "winner": "Milwaukee Brewers",
  "score": "2\u20137",
  "correct": true
 },
 {
  "date": "2026-06-30",
  "matchup": "San Diego Padres @ Chicago Cubs",
  "prob_home": 0.4798,
  "predicted": "San Diego Padres",
  "winner": "Chicago Cubs",
  "score": "7\u20139",
  "correct": false
 },
 {
  "date": "2026-06-30",
  "matchup": "Minnesota Twins @ Houston Astros",
  "prob_home": 0.4062,
  "predicted": "Minnesota Twins",
  "winner": "Houston Astros",
  "score": "4\u20136",
  "correct": false
 },
 {
  "date": "2026-06-30",
  "matchup": "Miami Marlins @ Colorado Rockies",
  "prob_home": 0.5276,
  "predicted": "Colorado Rockies",
  "winner": "Miami Marlins",
  "score": "14\u20133",
  "correct": false
 },
 {
  "date": "2026-06-30",
  "matchup": "Los Angeles Dodgers @ Athletics",
  "prob_home": 0.4585,
  "predicted": "Los Angeles Dodgers",
  "winner": "Los Angeles Dodgers",
  "score": "9\u20133",
  "correct": true
 },
 {
  "date": "2026-06-30",
  "matchup": "Los Angeles Angels @ Seattle Mariners",
  "prob_home": 0.8119,
  "predicted": "Seattle Mariners",
  "winner": "Seattle Mariners",
  "score": "3\u20138",
  "correct": true
 },
 {
  "date": "2026-06-30",
  "matchup": "San Francisco Giants @ Arizona Diamondbacks",
  "prob_home": 0.5173,
  "predicted": "Arizona Diamondbacks",
  "winner": "Arizona Diamondbacks",
  "score": "2\u20138",
  "correct": true
 },
 {
  "date": "2026-07-01",
  "matchup": "New York Mets @ Toronto Blue Jays",
  "prob_home": 0.8078,
  "predicted": "Toronto Blue Jays",
  "winner": "Toronto Blue Jays",
  "score": "3\u20139",
  "correct": true
 },
 {
  "date": "2026-07-01",
  "matchup": "Pittsburgh Pirates @ Philadelphia Phillies",
  "prob_home": 0.5155,
  "predicted": "Philadelphia Phillies",
  "winner": "Philadelphia Phillies",
  "score": "6\u201310",
  "correct": true
 },
 {
  "date": "2026-07-01",
  "matchup": "St. Louis Cardinals @ Atlanta Braves",
  "prob_home": 0.4799,
  "predicted": "St. Louis Cardinals",
  "winner": "Atlanta Braves",
  "score": "1\u20135",
  "correct": false
 },
 {
  "date": "2026-07-01",
  "matchup": "Tampa Bay Rays @ Kansas City Royals",
  "prob_home": 0.5606,
  "predicted": "Kansas City Royals",
  "winner": "Tampa Bay Rays",
  "score": "4\u20130",
  "correct": false
 },
 {
  "date": "2026-07-01",
  "matchup": "Minnesota Twins @ Houston Astros",
  "prob_home": 0.5322,
  "predicted": "Houston Astros",
  "winner": "Minnesota Twins",
  "score": "8\u20133",
  "correct": false
 },
 {
  "date": "2026-07-01",
  "matchup": "Cincinnati Reds @ Milwaukee Brewers",
  "prob_home": 0.5169,
  "predicted": "Milwaukee Brewers",
  "winner": "Milwaukee Brewers",
  "score": "2\u20134",
  "correct": true
 },
 {
  "date": "2026-07-01",
  "matchup": "Miami Marlins @ Colorado Rockies",
  "prob_home": 0.4719,
  "predicted": "Miami Marlins",
  "winner": "Colorado Rockies",
  "score": "3\u20136",
  "correct": false
 },
 {
  "date": "2026-07-01",
  "matchup": "Los Angeles Dodgers @ Athletics",
  "prob_home": 0.467,
  "predicted": "Los Angeles Dodgers",
  "winner": "Athletics",
  "score": "1\u20137",
  "correct": false
 },
 {
  "date": "2026-07-01",
  "matchup": "San Francisco Giants @ Arizona Diamondbacks",
  "prob_home": 0.4739,
  "predicted": "San Francisco Giants",
  "winner": "San Francisco Giants",
  "score": "6\u20134",
  "correct": true
 },
 {
  "date": "2026-07-02",
  "matchup": "Cincinnati Reds @ Milwaukee Brewers",
  "prob_home": 0.675,
  "predicted": "Milwaukee Brewers",
  "winner": "Cincinnati Reds",
  "score": "7\u20132",
  "correct": false
 },
 {
  "date": "2026-07-02",
  "matchup": "Miami Marlins @ Colorado Rockies",
  "prob_home": 0.412,
  "predicted": "Miami Marlins",
  "winner": "Colorado Rockies",
  "score": "4\u201314",
  "correct": false
 },
 {
  "date": "2026-07-02",
  "matchup": "Chicago White Sox @ Cleveland Guardians",
  "prob_home": 0.6244,
  "predicted": "Cleveland Guardians",
  "winner": "Cleveland Guardians",
  "score": "5\u20136",
  "correct": true
 },
 {
  "date": "2026-07-02",
  "matchup": "St. Louis Cardinals @ Atlanta Braves",
  "prob_home": 0.5435,
  "predicted": "Atlanta Braves",
  "winner": "St. Louis Cardinals",
  "score": "11\u20135",
  "correct": false
 },
 {
  "date": "2026-07-02",
  "matchup": "Tampa Bay Rays @ Kansas City Royals",
  "prob_home": 0.5189,
  "predicted": "Kansas City Royals",
  "winner": "Tampa Bay Rays",
  "score": "5\u20132",
  "correct": false
 },
 {
  "date": "2026-07-02",
  "matchup": "Detroit Tigers @ Texas Rangers",
  "prob_home": 0.5197,
  "predicted": "Texas Rangers",
  "winner": "Texas Rangers",
  "score": "4\u201310",
  "correct": true
 },
 {
  "date": "2026-07-02",
  "matchup": "Los Angeles Angels @ Seattle Mariners",
  "prob_home": 0.7422,
  "predicted": "Seattle Mariners",
  "winner": "Seattle Mariners",
  "score": "0\u20131",
  "correct": true
 },
 {
  "date": "2026-07-02",
  "matchup": "San Diego Padres @ Los Angeles Dodgers",
  "prob_home": 0.5401,
  "predicted": "Los Angeles Dodgers",
  "winner": "Los Angeles Dodgers",
  "score": "7\u201312",
  "correct": true
 },
 {
  "date": "2026-07-03",
  "matchup": "St. Louis Cardinals @ Chicago Cubs",
  "prob_home": 0.5475,
  "predicted": "Chicago Cubs",
  "winner": "St. Louis Cardinals",
  "score": "17\u20131",
  "correct": false
 },
 {
  "date": "2026-07-03",
  "matchup": "Pittsburgh Pirates @ Washington Nationals",
  "prob_home": 0.6915,
  "predicted": "Washington Nationals",
  "winner": "Washington Nationals",
  "score": "5\u20139",
  "correct": true
 },
 {
  "date": "2026-07-03",
  "matchup": "Minnesota Twins @ New York Yankees",
  "prob_home": 0.5867,
  "predicted": "New York Yankees",
  "winner": "New York Yankees",
  "score": "2\u20135",
  "correct": true
 },
 {
  "date": "2026-07-03",
  "matchup": "Baltimore Orioles @ Cincinnati Reds",
  "prob_home": 0.4162,
  "predicted": "Baltimore Orioles",
  "winner": "Baltimore Orioles",
  "score": "3\u20130",
  "correct": true
 },
 {
  "date": "2026-07-03",
  "matchup": "Chicago White Sox @ Cleveland Guardians",
  "prob_home": 0.5395,
  "predicted": "Cleveland Guardians",
  "winner": "Cleveland Guardians",
  "score": "3\u20134",
  "correct": true
 },
 {
  "date": "2026-07-03",
  "matchup": "New York Mets @ Atlanta Braves",
  "prob_home": 0.588,
  "predicted": "Atlanta Braves",
  "winner": "Atlanta Braves",
  "score": "3\u20135",
  "correct": true
 },
 {
  "date": "2026-07-03",
  "matchup": "San Francisco Giants @ Colorado Rockies",
  "prob_home": 0.5664,
  "predicted": "Colorado Rockies",
  "winner": "Colorado Rockies",
  "score": "3\u201315",
  "correct": true
 },
 {
  "date": "2026-07-03",
  "matchup": "Tampa Bay Rays @ Houston Astros",
  "prob_home": 0.4103,
  "predicted": "Tampa Bay Rays",
  "winner": "Tampa Bay Rays",
  "score": "3\u20131",
  "correct": true
 },
 {
  "date": "2026-07-03",
  "matchup": "Boston Red Sox @ Los Angeles Angels",
  "prob_home": 0.5134,
  "predicted": "Los Angeles Angels",
  "winner": "Boston Red Sox",
  "score": "5\u20132",
  "correct": false
 },
 {
  "date": "2026-07-03",
  "matchup": "Miami Marlins @ Athletics",
  "prob_home": 0.5686,
  "predicted": "Athletics",
  "winner": "Miami Marlins",
  "score": "12\u20135",
  "correct": false
 },
 {
  "date": "2026-07-03",
  "matchup": "Milwaukee Brewers @ Arizona Diamondbacks",
  "prob_home": 0.4976,
  "predicted": "Milwaukee Brewers",
  "winner": "Milwaukee Brewers",
  "score": "7\u20134",
  "correct": true
 },
 {
  "date": "2026-07-03",
  "matchup": "San Diego Padres @ Los Angeles Dodgers",
  "prob_home": 0.5846,
  "predicted": "Los Angeles Dodgers",
  "winner": "Los Angeles Dodgers",
  "score": "3\u20134",
  "correct": true
 },
 {
  "date": "2026-07-03",
  "matchup": "Toronto Blue Jays @ Seattle Mariners",
  "prob_home": 0.46,
  "predicted": "Toronto Blue Jays",
  "winner": "Toronto Blue Jays",
  "score": "2\u20130",
  "correct": true
 },
 {
  "date": "2026-07-04",
  "matchup": "Minnesota Twins @ New York Yankees",
  "prob_home": 0.4239,
  "predicted": "Minnesota Twins",
  "winner": "Minnesota Twins",
  "score": "11\u20134",
  "correct": true
 },
 {
  "date": "2026-07-04",
  "matchup": "Detroit Tigers @ Texas Rangers",
  "prob_home": 0.551,
  "predicted": "Texas Rangers",
  "winner": "Detroit Tigers",
  "score": "3\u20130",
  "correct": false
 },
 {
  "date": "2026-07-04",
  "matchup": "Toronto Blue Jays @ Seattle Mariners",
  "prob_home": 0.658,
  "predicted": "Seattle Mariners",
  "winner": "Seattle Mariners",
  "score": "0\u201311",
  "correct": true
 },
 {
  "date": "2026-07-04",
  "matchup": "Baltimore Orioles @ Cincinnati Reds",
  "prob_home": 0.5054,
  "predicted": "Cincinnati Reds",
  "winner": "Baltimore Orioles",
  "score": "8\u20135",
  "correct": false
 },
 {
  "date": "2026-07-04",
  "matchup": "Tampa Bay Rays @ Houston Astros",
  "prob_home": 0.6469,
  "predicted": "Houston Astros",
  "winner": "Houston Astros",
  "score": "8\u201310",
  "correct": true
 },
 {
  "date": "2026-07-04",
  "matchup": "Chicago White Sox @ Cleveland Guardians",
  "prob_home": 0.514,
  "predicted": "Cleveland Guardians",
  "winner": "Chicago White Sox",
  "score": "3\u20131",
  "correct": false
 },
 {
  "date": "2026-07-04",
  "matchup": "St. Louis Cardinals @ Chicago Cubs",
  "prob_home": 0.505,
  "predicted": "Chicago Cubs",
  "winner": "St. Louis Cardinals",
  "score": "3\u20130",
  "correct": false
 },
 {
  "date": "2026-07-04",
  "matchup": "New York Mets @ Atlanta Braves",
  "prob_home": 0.7707,
  "predicted": "Atlanta Braves",
  "winner": "Atlanta Braves",
  "score": "3\u201314",
  "correct": true
 },
 {
  "date": "2026-07-04",
  "matchup": "San Francisco Giants @ Colorado Rockies",
  "prob_home": 0.4108,
  "predicted": "San Francisco Giants",
  "winner": "San Francisco Giants",
  "score": "6\u20134",
  "correct": true
 },
 {
  "date": "2026-07-04",
  "matchup": "Philadelphia Phillies @ Kansas City Royals",
  "prob_home": 0.5961,
  "predicted": "Kansas City Royals",
  "winner": "Philadelphia Phillies",
  "score": "6\u20131",
  "correct": false
 },
 {
  "date": "2026-07-04",
  "matchup": "Boston Red Sox @ Los Angeles Angels",
  "prob_home": 0.4845,
  "predicted": "Boston Red Sox",
  "winner": "Boston Red Sox",
  "score": "8\u20131",
  "correct": true
 },
 {
  "date": "2026-07-04",
  "matchup": "Miami Marlins @ Athletics",
  "prob_home": 0.5961,
  "predicted": "Athletics",
  "winner": "Miami Marlins",
  "score": "7\u20132",
  "correct": false
 },
 {
  "date": "2026-07-04",
  "matchup": "Milwaukee Brewers @ Arizona Diamondbacks",
  "prob_home": 0.1875,
  "predicted": "Milwaukee Brewers",
  "winner": "Arizona Diamondbacks",
  "score": "3\u20134",
  "correct": false
 },
 {
  "date": "2026-07-04",
  "matchup": "San Diego Padres @ Los Angeles Dodgers",
  "prob_home": 0.514,
  "predicted": "Los Angeles Dodgers",
  "winner": "Los Angeles Dodgers",
  "score": "0\u20133",
  "correct": true
 },
 {
  "date": "2026-07-05",
  "matchup": "New York Mets @ Atlanta Braves",
  "prob_home": 0.5439,
  "predicted": "Atlanta Braves",
  "winner": "New York Mets",
  "score": "10\u20139",
  "correct": false
 },
 {
  "date": "2026-07-05",
  "matchup": "Pittsburgh Pirates @ Washington Nationals",
  "prob_home": 0.503,
  "predicted": "Washington Nationals",
  "winner": "Pittsburgh Pirates",
  "score": "11\u20135",
  "correct": false
 },
 {
  "date": "2026-07-05",
  "matchup": "Minnesota Twins @ New York Yankees",
  "prob_home": 0.572,
  "predicted": "New York Yankees",
  "winner": "Minnesota Twins",
  "score": "6\u20131",
  "correct": false
 },
 {
  "date": "2026-07-05",
  "matchup": "Chicago White Sox @ Cleveland Guardians",
  "prob_home": 0.5799,
  "predicted": "Cleveland Guardians",
  "winner": "Chicago White Sox",
  "score": "7\u20136",
  "correct": false
 },
 {
  "date": "2026-07-05",
  "matchup": "St. Louis Cardinals @ Chicago Cubs",
  "prob_home": 0.6489,
  "predicted": "Chicago Cubs",
  "winner": "Chicago Cubs",
  "score": "4\u20136",
  "correct": true
 },
 {
  "date": "2026-07-05",
  "matchup": "Philadelphia Phillies @ Kansas City Royals",
  "prob_home": 0.488,
  "predicted": "Philadelphia Phillies",
  "winner": "Kansas City Royals",
  "score": "2\u20135",
  "correct": false
 },
 {
  "date": "2026-07-05",
  "matchup": "Tampa Bay Rays @ Houston Astros",
  "prob_home": 0.6754,
  "predicted": "Houston Astros",
  "winner": "Houston Astros",
  "score": "0\u20132",
  "correct": true
 },
 {
  "date": "2026-07-05",
  "matchup": "Detroit Tigers @ Texas Rangers",
  "prob_home": 0.3621,
  "predicted": "Detroit Tigers",
  "winner": "Detroit Tigers",
  "score": "6\u20133",
  "correct": true
 },
 {
  "date": "2026-07-05",
  "matchup": "San Francisco Giants @ Colorado Rockies",
  "prob_home": 0.5166,
  "predicted": "Colorado Rockies",
  "winner": "Colorado Rockies",
  "score": "6\u20137",
  "correct": true
 },
 {
  "date": "2026-07-05",
  "matchup": "Milwaukee Brewers @ Arizona Diamondbacks",
  "prob_home": 0.896,
  "predicted": "Arizona Diamondbacks",
  "winner": "Milwaukee Brewers",
  "score": "3\u20132",
  "correct": false
 },
 {
  "date": "2026-07-05",
  "matchup": "Miami Marlins @ Athletics",
  "prob_home": 0.7097,
  "predicted": "Athletics",
  "winner": "Miami Marlins",
  "score": "9\u20138",
  "correct": false
 },
 {
  "date": "2026-07-05",
  "matchup": "Toronto Blue Jays @ Seattle Mariners",
  "prob_home": 0.5092,
  "predicted": "Seattle Mariners",
  "winner": "Seattle Mariners",
  "score": "0\u20134",
  "correct": true
 },
 {
  "date": "2026-07-05",
  "matchup": "San Diego Padres @ Los Angeles Dodgers",
  "prob_home": 0.5092,
  "predicted": "Los Angeles Dodgers",
  "winner": "San Diego Padres",
  "score": "5\u20132",
  "correct": false
 },
 {
  "date": "2026-07-05",
  "matchup": "Boston Red Sox @ Los Angeles Angels",
  "prob_home": 0.4274,
  "predicted": "Boston Red Sox",
  "winner": "Boston Red Sox",
  "score": "7\u20135",
  "correct": true
 },
 {
  "date": "2026-07-06",
  "matchup": "Philadelphia Phillies @ Kansas City Royals",
  "prob_home": 0.6129,
  "predicted": "Kansas City Royals",
  "winner": "Kansas City Royals",
  "score": "1\u201315",
  "correct": true
 },
 {
  "date": "2026-07-06",
  "matchup": "New York Yankees @ Tampa Bay Rays",
  "prob_home": 0.5218,
  "predicted": "Tampa Bay Rays",
  "winner": "New York Yankees",
  "score": "5\u20131",
  "correct": false
 },
 {
  "date": "2026-07-06",
  "matchup": "Houston Astros @ Washington Nationals",
  "prob_home": 0.5308,
  "predicted": "Washington Nationals",
  "winner": "Washington Nationals",
  "score": "11\u201312",
  "correct": true
 },
 {
  "date": "2026-07-06",
  "matchup": "New York Mets @ Atlanta Braves",
  "prob_home": 0.6436,
  "predicted": "Atlanta Braves",
  "winner": "New York Mets",
  "score": "7\u20136",
  "correct": false
 },
 {
  "date": "2026-07-06",
  "matchup": "Milwaukee Brewers @ St. Louis Cardinals",
  "prob_home": 0.5129,
  "predicted": "St. Louis Cardinals",
  "winner": "Milwaukee Brewers",
  "score": "4\u20133",
  "correct": false
 },
 {
  "date": "2026-07-06",
  "matchup": "Arizona Diamondbacks @ San Diego Padres",
  "prob_home": 0.4543,
  "predicted": "Arizona Diamondbacks",
  "winner": "Arizona Diamondbacks",
  "score": "8\u20130",
  "correct": true
 },
 {
  "date": "2026-07-06",
  "matchup": "Toronto Blue Jays @ San Francisco Giants",
  "prob_home": 0.5218,
  "predicted": "San Francisco Giants",
  "winner": "San Francisco Giants",
  "score": "1\u201310",
  "correct": true
 },
 {
  "date": "2026-07-06",
  "matchup": "Colorado Rockies @ Los Angeles Dodgers",
  "prob_home": 0.6129,
  "predicted": "Los Angeles Dodgers",
  "winner": "Los Angeles Dodgers",
  "score": "7\u20138",
  "correct": true
 },
 {
  "date": "2026-07-07",
  "matchup": "Milwaukee Brewers @ St. Louis Cardinals",
  "prob_home": 0.4396,
  "predicted": "Milwaukee Brewers",
  "winner": "Milwaukee Brewers",
  "score": "10\u20132",
  "correct": true
 },
 {
  "date": "2026-07-07",
  "matchup": "Chicago Cubs @ Baltimore Orioles",
  "prob_home": 0.574,
  "predicted": "Baltimore Orioles",
  "winner": "Chicago Cubs",
  "score": "5\u20132",
  "correct": false
 },
 {
  "date": "2026-07-07",
  "matchup": "Athletics @ Detroit Tigers",
  "prob_home": 0.5999,
  "predicted": "Detroit Tigers",
  "winner": "Detroit Tigers",
  "score": "2\u20136",
  "correct": true
 },
 {
  "date": "2026-07-07",
  "matchup": "Atlanta Braves @ Pittsburgh Pirates",
  "prob_home": 0.5998,
  "predicted": "Pittsburgh Pirates",
  "winner": "Pittsburgh Pirates",
  "score": "4\u201312",
  "correct": true
 },
 {
  "date": "2026-07-07",
  "matchup": "Seattle Mariners @ Miami Marlins",
  "prob_home": 0.5364,
  "predicted": "Miami Marlins",
  "winner": "Miami Marlins",
  "score": "5\u20136",
  "correct": true
 },
 {
  "date": "2026-07-07",
  "matchup": "New York Yankees @ Tampa Bay Rays",
  "prob_home": 0.6105,
  "predicted": "Tampa Bay Rays",
  "winner": "Tampa Bay Rays",
  "score": "4\u20136",
  "correct": true
 },
 {
  "date": "2026-07-07",
  "matchup": "Houston Astros @ Washington Nationals",
  "prob_home": 0.3519,
  "predicted": "Houston Astros",
  "winner": "Houston Astros",
  "score": "6\u20133",
  "correct": true
 },
 {
  "date": "2026-07-07",
  "matchup": "Kansas City Royals @ New York Mets",
  "prob_home": 0.7479,
  "predicted": "New York Mets",
  "winner": "Kansas City Royals",
  "score": "16\u201312",
  "correct": false
 },
 {
  "date": "2026-07-07",
  "matchup": "Philadelphia Phillies @ Cincinnati Reds",
  "prob_home": 0.4854,
  "predicted": "Philadelphia Phillies",
  "winner": "Philadelphia Phillies",
  "score": "4\u20131",
  "correct": true
 },
 {
  "date": "2026-07-07",
  "matchup": "Cleveland Guardians @ Minnesota Twins",
  "prob_home": 0.4686,
  "predicted": "Cleveland Guardians",
  "winner": "Minnesota Twins",
  "score": "1\u20133",
  "correct": false
 },
 {
  "date": "2026-07-07",
  "matchup": "Boston Red Sox @ Chicago White Sox",
  "prob_home": 0.3838,
  "predicted": "Boston Red Sox",
  "winner": "Boston Red Sox",
  "score": "8\u20131",
  "correct": true
 },
 {
  "date": "2026-07-07",
  "matchup": "Los Angeles Angels @ Texas Rangers",
  "prob_home": 0.6835,
  "predicted": "Texas Rangers",
  "winner": "Texas Rangers",
  "score": "3\u20138",
  "correct": true
 },
 {
  "date": "2026-07-07",
  "matchup": "Arizona Diamondbacks @ San Diego Padres",
  "prob_home": 0.5364,
  "predicted": "San Diego Padres",
  "winner": "San Diego Padres",
  "score": "1\u20134",
  "correct": true
 },
 {
  "date": "2026-07-07",
  "matchup": "Toronto Blue Jays @ San Francisco Giants",
  "prob_home": 0.6483,
  "predicted": "San Francisco Giants",
  "winner": "Toronto Blue Jays",
  "score": "9\u20133",
  "correct": false
 },
 {
  "date": "2026-07-07",
  "matchup": "Colorado Rockies @ Los Angeles Dodgers",
  "prob_home": 0.6703,
  "predicted": "Los Angeles Dodgers",
  "winner": "Colorado Rockies",
  "score": "4\u20133",
  "correct": false
 },
 {
  "date": "2026-07-08",
  "matchup": "Toronto Blue Jays @ San Francisco Giants",
  "prob_home": 0.467,
  "predicted": "Toronto Blue Jays",
  "winner": "Toronto Blue Jays",
  "score": "10\u20130",
  "correct": true
 },
 {
  "date": "2026-07-08",
  "matchup": "Chicago Cubs @ Baltimore Orioles",
  "prob_home": 0.6733,
  "predicted": "Baltimore Orioles",
  "winner": "Chicago Cubs",
  "score": "9\u20137",
  "correct": false
 },
 {
  "date": "2026-07-08",
  "matchup": "Athletics @ Detroit Tigers",
  "prob_home": 0.5427,
  "predicted": "Detroit Tigers",
  "winner": "Detroit Tigers",
  "score": "1\u20136",
  "correct": true
 },
 {
  "date": "2026-07-08",
  "matchup": "Atlanta Braves @ Pittsburgh Pirates",
  "prob_home": 0.6826,
  "predicted": "Pittsburgh Pirates",
  "winner": "Atlanta Braves",
  "score": "3\u20130",
  "correct": false
 },
 {
  "date": "2026-07-08",
  "matchup": "Seattle Mariners @ Miami Marlins",
  "prob_home": 0.6006,
  "predicted": "Miami Marlins",
  "winner": "Miami Marlins",
  "score": "0\u20132",
  "correct": true
 },
 {
  "date": "2026-07-08",
  "matchup": "New York Yankees @ Tampa Bay Rays",
  "prob_home": 0.6223,
  "predicted": "Tampa Bay Rays",
  "winner": "Tampa Bay Rays",
  "score": "0\u20133",
  "correct": true
 },
 {
  "date": "2026-07-08",
  "matchup": "Houston Astros @ Washington Nationals",
  "prob_home": 0.6125,
  "predicted": "Washington Nationals",
  "winner": "Washington Nationals",
  "score": "2\u20138",
  "correct": true
 },
 {
  "date": "2026-07-08",
  "matchup": "Kansas City Royals @ New York Mets",
  "prob_home": 0.4389,
  "predicted": "Kansas City Royals",
  "winner": "New York Mets",
  "score": "2\u20136",
  "correct": false
 },
 {
  "date": "2026-07-08",
  "matchup": "Philadelphia Phillies @ Cincinnati Reds",
  "prob_home": 0.5151,
  "predicted": "Cincinnati Reds",
  "winner": "Cincinnati Reds",
  "score": "5\u201311",
  "correct": true
 },
 {
  "date": "2026-07-08",
  "matchup": "Cleveland Guardians @ Minnesota Twins",
  "prob_home": 0.5368,
  "predicted": "Minnesota Twins",
  "winner": "Minnesota Twins",
  "score": "5\u20136",
  "correct": true
 },
 {
  "date": "2026-07-08",
  "matchup": "Boston Red Sox @ Chicago White Sox",
  "prob_home": 0.3811,
  "predicted": "Boston Red Sox",
  "winner": "Boston Red Sox",
  "score": "5\u20130",
  "correct": true
 },
 {
  "date": "2026-07-08",
  "matchup": "Milwaukee Brewers @ St. Louis Cardinals",
  "prob_home": 0.4321,
  "predicted": "Milwaukee Brewers",
  "winner": "St. Louis Cardinals",
  "score": "1\u20135",
  "correct": false
 },
 {
  "date": "2026-07-08",
  "matchup": "Los Angeles Angels @ Texas Rangers",
  "prob_home": 0.5141,
  "predicted": "Texas Rangers",
  "winner": "Los Angeles Angels",
  "score": "13\u20131",
  "correct": false
 },
 {
  "date": "2026-07-08",
  "matchup": "Colorado Rockies @ Los Angeles Dodgers",
  "prob_home": 0.5541,
  "predicted": "Los Angeles Dodgers",
  "winner": "Los Angeles Dodgers",
  "score": "3\u20134",
  "correct": true
 },
 {
  "date": "2026-07-08",
  "matchup": "Arizona Diamondbacks @ San Diego Padres",
  "prob_home": 0.6729,
  "predicted": "San Diego Padres",
  "winner": "San Diego Padres",
  "score": "4\u201310",
  "correct": true
 },
 {
  "date": "2026-07-09",
  "matchup": "Athletics @ Detroit Tigers",
  "prob_home": 0.5605,
  "predicted": "Detroit Tigers",
  "winner": "Detroit Tigers",
  "score": "1\u20134",
  "correct": true
 },
 {
  "date": "2026-07-09",
  "matchup": "Seattle Mariners @ Miami Marlins",
  "prob_home": 0.3966,
  "predicted": "Seattle Mariners",
  "winner": "Miami Marlins",
  "score": "4\u20138",
  "correct": false
 },
 {
  "date": "2026-07-09",
  "matchup": "Philadelphia Phillies @ Cincinnati Reds",
  "prob_home": 0.479,
  "predicted": "Philadelphia Phillies",
  "winner": "Philadelphia Phillies",
  "score": "1\u20130",
  "correct": true
 },
 {
  "date": "2026-07-09",
  "matchup": "Milwaukee Brewers @ St. Louis Cardinals",
  "prob_home": 0.4293,
  "predicted": "Milwaukee Brewers",
  "winner": "Milwaukee Brewers",
  "score": "8\u20134",
  "correct": true
 },
 {
  "date": "2026-07-09",
  "matchup": "Los Angeles Angels @ Texas Rangers",
  "prob_home": 0.4924,
  "predicted": "Los Angeles Angels",
  "winner": "Texas Rangers",
  "score": "6\u20137",
  "correct": false
 },
 {
  "date": "2026-07-09",
  "matchup": "Arizona Diamondbacks @ San Diego Padres",
  "prob_home": 0.4514,
  "predicted": "Arizona Diamondbacks",
  "winner": "Arizona Diamondbacks",
  "score": "3\u20131",
  "correct": true
 },
 {
  "date": "2026-07-09",
  "matchup": "Colorado Rockies @ San Francisco Giants",
  "prob_home": 0.4293,
  "predicted": "Colorado Rockies",
  "winner": "San Francisco Giants",
  "score": "2\u20138",
  "correct": false
 },
 {
  "date": "2026-07-10",
  "matchup": "Philadelphia Phillies @ Detroit Tigers",
  "prob_home": 0.5795,
  "predicted": "Detroit Tigers",
  "winner": "Detroit Tigers",
  "score": "2\u201310",
  "correct": true
 },
 {
  "date": "2026-07-10",
  "matchup": "New York Yankees @ Washington Nationals",
  "prob_home": 0.4361,
  "predicted": "New York Yankees",
  "winner": "New York Yankees",
  "score": "5\u20133",
  "correct": true
 },
 {
  "date": "2026-07-10",
  "matchup": "Kansas City Royals @ Baltimore Orioles",
  "prob_home": 0.7044,
  "predicted": "Baltimore Orioles",
  "winner": "Baltimore Orioles",
  "score": "3\u20135",
  "correct": true
 },
 {
  "date": "2026-07-10",
  "matchup": "Chicago Cubs @ Cincinnati Reds",
  "prob_home": 0.4706,
  "predicted": "Chicago Cubs",
  "winner": "Cincinnati Reds",
  "score": "0\u20134",
  "correct": false
 },
 {
  "date": "2026-07-10",
  "matchup": "Seattle Mariners @ Tampa Bay Rays",
  "prob_home": 0.5179,
  "predicted": "Tampa Bay Rays",
  "winner": "Tampa Bay Rays",
  "score": "2\u20137",
  "correct": true
 },
 {
  "date": "2026-07-10",
  "matchup": "Cleveland Guardians @ Miami Marlins",
  "prob_home": 0.657,
  "predicted": "Miami Marlins",
  "winner": "Cleveland Guardians",
  "score": "3\u20132",
  "correct": false
 },
 {
  "date": "2026-07-10",
  "matchup": "Boston Red Sox @ New York Mets",
  "prob_home": 0.4741,
  "predicted": "Boston Red Sox",
  "winner": "Boston Red Sox",
  "score": "6\u20132",
  "correct": true
 },
 {
  "date": "2026-07-10",
  "matchup": "Athletics @ Chicago White Sox",
  "prob_home": 0.5167,
  "predicted": "Chicago White Sox",
  "winner": "Chicago White Sox",
  "score": "1\u201314",
  "correct": true
 },
 {
  "date": "2026-07-10",
  "matchup": "Houston Astros @ Texas Rangers",
  "prob_home": 0.4572,
  "predicted": "Houston Astros",
  "winner": "Texas Rangers",
  "score": "3\u20137",
  "correct": false
 },
 {
  "date": "2026-07-10",
  "matchup": "Los Angeles Angels @ Minnesota Twins",
  "prob_home": 0.5447,
  "predicted": "Minnesota Twins",
  "winner": "Los Angeles Angels",
  "score": "4\u20133",
  "correct": false
 },
 {
  "date": "2026-07-10",
  "matchup": "Atlanta Braves @ St. Louis Cardinals",
  "prob_home": 0.3937,
  "predicted": "Atlanta Braves",
  "winner": "St. Louis Cardinals",
  "score": "1\u20132",
  "correct": false
 },
 {
  "date": "2026-07-10",
  "matchup": "Toronto Blue Jays @ San Diego Padres",
  "prob_home": 0.4373,
  "predicted": "Toronto Blue Jays",
  "winner": "Toronto Blue Jays",
  "score": "5\u20133",
  "correct": true
 },
 {
  "date": "2026-07-10",
  "matchup": "Arizona Diamondbacks @ Los Angeles Dodgers",
  "prob_home": 0.4741,
  "predicted": "Arizona Diamondbacks",
  "winner": "Arizona Diamondbacks",
  "score": "9\u20133",
  "correct": true
 },
 {
  "date": "2026-07-10",
  "matchup": "Colorado Rockies @ San Francisco Giants",
  "prob_home": 0.6193,
  "predicted": "San Francisco Giants",
  "winner": "Colorado Rockies",
  "score": "4\u20133",
  "correct": false
 },
 {
  "date": "2026-07-11",
  "matchup": "Milwaukee Brewers @ Pittsburgh Pirates",
  "prob_home": 0.5427,
  "predicted": "Pittsburgh Pirates",
  "winner": "Pittsburgh Pirates",
  "score": "6\u20137",
  "correct": true
 },
 {
  "date": "2026-07-11",
  "matchup": "Milwaukee Brewers @ Pittsburgh Pirates",
  "prob_home": 0.4783,
  "predicted": "Milwaukee Brewers",
  "winner": "Pittsburgh Pirates",
  "score": "2\u20133",
  "correct": false
 },
 {
  "date": "2026-07-11",
  "matchup": "Los Angeles Angels @ Minnesota Twins",
  "prob_home": 0.7149,
  "predicted": "Minnesota Twins",
  "winner": "Minnesota Twins",
  "score": "3\u20135",
  "correct": true
 },
 {
  "date": "2026-07-11",
  "matchup": "Athletics @ Chicago White Sox",
  "prob_home": 0.4132,
  "predicted": "Athletics",
  "winner": "Chicago White Sox",
  "score": "0\u20131",
  "correct": false
 },
 {
  "date": "2026-07-11",
  "matchup": "Colorado Rockies @ San Francisco Giants",
  "prob_home": 0.5504,
  "predicted": "San Francisco Giants",
  "winner": "San Francisco Giants",
  "score": "2\u20134",
  "correct": true
 },
 {
  "date": "2026-07-11",
  "matchup": "New York Yankees @ Washington Nationals",
  "prob_home": 0.425,
  "predicted": "New York Yankees",
  "winner": "New York Yankees",
  "score": "4\u20132",
  "correct": true
 },
 {
  "date": "2026-07-11",
  "matchup": "Boston Red Sox @ New York Mets",
  "prob_home": 0.3952,
  "predicted": "Boston Red Sox",
  "winner": "Boston Red Sox",
  "score": "4\u20130",
  "correct": true
 },
 {
  "date": "2026-07-11",
  "matchup": "Seattle Mariners @ Tampa Bay Rays",
  "prob_home": 0.4594,
  "predicted": "Seattle Mariners",
  "winner": "Tampa Bay Rays",
  "score": "1\u20136",
  "correct": false
 },
 {
  "date": "2026-07-11",
  "matchup": "Cleveland Guardians @ Miami Marlins",
  "prob_home": 0.5422,
  "predicted": "Miami Marlins",
  "winner": "Cleveland Guardians",
  "score": "4\u20131",
  "correct": false
 },
 {
  "date": "2026-07-11",
  "matchup": "Philadelphia Phillies @ Detroit Tigers",
  "prob_home": 0.6054,
  "predicted": "Detroit Tigers",
  "winner": "Philadelphia Phillies",
  "score": "4\u20132",
  "correct": false
 },
 {
  "date": "2026-07-11",
  "matchup": "Kansas City Royals @ Baltimore Orioles",
  "prob_home": 0.4796,
  "predicted": "Kansas City Royals",
  "winner": "Baltimore Orioles",
  "score": "1\u20136",
  "correct": false
 },
 {
  "date": "2026-07-11",
  "matchup": "Houston Astros @ Texas Rangers",
  "prob_home": 0.425,
  "predicted": "Houston Astros",
  "winner": "Houston Astros",
  "score": "9\u20133",
  "correct": true
 },
 {
  "date": "2026-07-11",
  "matchup": "Chicago Cubs @ Cincinnati Reds",
  "prob_home": 0.3922,
  "predicted": "Chicago Cubs",
  "winner": "Chicago Cubs",
  "score": "5\u20133",
  "correct": true
 },
 {
  "date": "2026-07-11",
  "matchup": "Atlanta Braves @ St. Louis Cardinals",
  "prob_home": 0.4094,
  "predicted": "Atlanta Braves",
  "winner": "St. Louis Cardinals",
  "score": "1\u20134",
  "correct": false
 },
 {
  "date": "2026-07-11",
  "matchup": "Toronto Blue Jays @ San Diego Padres",
  "prob_home": 0.4324,
  "predicted": "Toronto Blue Jays",
  "winner": "San Diego Padres",
  "score": "7\u20138",
  "correct": false
 },
 {
  "date": "2026-07-11",
  "matchup": "Arizona Diamondbacks @ Los Angeles Dodgers",
  "prob_home": 0.6915,
  "predicted": "Los Angeles Dodgers",
  "winner": "Arizona Diamondbacks",
  "score": "9\u20132",
  "correct": false
 },
 {
  "date": "2026-07-12",
  "matchup": "Milwaukee Brewers @ Pittsburgh Pirates",
  "prob_home": 0.4953,
  "predicted": "Milwaukee Brewers",
  "winner": "Pittsburgh Pirates",
  "score": "5\u201314",
  "correct": false
 },
 {
  "date": "2026-07-12",
  "matchup": "Kansas City Royals @ Baltimore Orioles",
  "prob_home": 0.7712,
  "predicted": "Baltimore Orioles",
  "winner": "Baltimore Orioles",
  "score": "2\u20138",
  "correct": true
 },
 {
  "date": "2026-07-12",
  "matchup": "New York Yankees @ Washington Nationals",
  "prob_home": 0.5752,
  "predicted": "Washington Nationals",
  "winner": "New York Yankees",
  "score": "5\u20133",
  "correct": false
 },
 {
  "date": "2026-07-12",
  "matchup": "Chicago Cubs @ Cincinnati Reds",
  "prob_home": 0.6153,
  "predicted": "Cincinnati Reds",
  "winner": "Chicago Cubs",
  "score": "8\u20134",
  "correct": false
 },
 {
  "date": "2026-07-12",
  "matchup": "Boston Red Sox @ New York Mets",
  "prob_home": 0.4872,
  "predicted": "Boston Red Sox",
  "winner": "Boston Red Sox",
  "score": "3\u20132",
  "correct": true
 },
 {
  "date": "2026-07-12",
  "matchup": "Seattle Mariners @ Tampa Bay Rays",
  "prob_home": 0.4213,
  "predicted": "Seattle Mariners",
  "winner": "Seattle Mariners",
  "score": "8\u20132",
  "correct": true
 },
 {
  "date": "2026-07-12",
  "matchup": "Philadelphia Phillies @ Detroit Tigers",
  "prob_home": 0.4872,
  "predicted": "Philadelphia Phillies",
  "winner": "Philadelphia Phillies",
  "score": "5\u20130",
  "correct": true
 },
 {
  "date": "2026-07-12",
  "matchup": "Cleveland Guardians @ Miami Marlins",
  "prob_home": 0.6451,
  "predicted": "Miami Marlins",
  "winner": "Cleveland Guardians",
  "score": "5\u20132",
  "correct": false
 },
 {
  "date": "2026-07-12",
  "matchup": "Los Angeles Angels @ Minnesota Twins",
  "prob_home": 0.6219,
  "predicted": "Minnesota Twins",
  "winner": "Minnesota Twins",
  "score": "2\u20134",
  "correct": true
 },
 {
  "date": "2026-07-12",
  "matchup": "Athletics @ Chicago White Sox",
  "prob_home": 0.4512,
  "predicted": "Athletics",
  "winner": "Chicago White Sox",
  "score": "1\u20139",
  "correct": false
 },
 {
  "date": "2026-07-12",
  "matchup": "Atlanta Braves @ St. Louis Cardinals",
  "prob_home": 0.6471,
  "predicted": "St. Louis Cardinals",
  "winner": "Atlanta Braves",
  "score": "4\u20133",
  "correct": false
 },
 {
  "date": "2026-07-12",
  "matchup": "Houston Astros @ Texas Rangers",
  "prob_home": 0.891,
  "predicted": "Texas Rangers",
  "winner": "Texas Rangers",
  "score": "5\u20136",
  "correct": true
 },
 {
  "date": "2026-07-12",
  "matchup": "Colorado Rockies @ San Francisco Giants",
  "prob_home": 0.4872,
  "predicted": "Colorado Rockies",
  "winner": "San Francisco Giants",
  "score": "1\u20133",
  "correct": false
 },
 {
  "date": "2026-07-12",
  "matchup": "Arizona Diamondbacks @ Los Angeles Dodgers",
  "prob_home": 0.4278,
  "predicted": "Arizona Diamondbacks",
  "winner": "Arizona Diamondbacks",
  "score": "5\u20133",
  "correct": true
 },
 {
  "date": "2026-07-12",
  "matchup": "Toronto Blue Jays @ San Diego Padres",
  "prob_home": 0.5169,
  "predicted": "San Diego Padres",
  "winner": "San Diego Padres",
  "score": "4\u20135",
  "correct": true
 },
 {
  "date": "2026-07-16",
  "matchup": "New York Mets @ Philadelphia Phillies",
  "prob_home": 0.6159,
  "predicted": "Philadelphia Phillies",
  "winner": "New York Mets",
  "score": "4\u20131",
  "correct": false
 },
 {
  "date": "2026-07-17",
  "matchup": "Tampa Bay Rays @ Boston Red Sox",
  "prob_home": 0.665,
  "predicted": "Boston Red Sox",
  "winner": "Boston Red Sox",
  "score": "0\u201310",
  "correct": true
 },
 {
  "date": "2026-07-17",
  "matchup": "Tampa Bay Rays @ Boston Red Sox",
  "prob_home": 0.4245,
  "predicted": "Tampa Bay Rays",
  "winner": "Boston Red Sox",
  "score": "3\u20135",
  "correct": false
 },
 {
  "date": "2026-07-17",
  "matchup": "Los Angeles Dodgers @ New York Yankees",
  "prob_home": 0.5622,
  "predicted": "New York Yankees",
  "winner": "Los Angeles Dodgers",
  "score": "2\u20131",
  "correct": false
 },
 {
  "date": "2026-07-17",
  "matchup": "Texas Rangers @ Atlanta Braves",
  "prob_home": 0.6254,
  "predicted": "Atlanta Braves",
  "winner": "Atlanta Braves",
  "score": "1\u201315",
  "correct": true
 },
 {
  "date": "2026-07-17",
  "matchup": "Chicago White Sox @ Toronto Blue Jays",
  "prob_home": 0.5552,
  "predicted": "Toronto Blue Jays",
  "winner": "Chicago White Sox",
  "score": "12\u20134",
  "correct": false
 },
 {
  "date": "2026-07-17",
  "matchup": "Miami Marlins @ Milwaukee Brewers",
  "prob_home": 0.7475,
  "predicted": "Milwaukee Brewers",
  "winner": "Milwaukee Brewers",
  "score": "1\u20132",
  "correct": true
 },
 {
  "date": "2026-07-17",
  "matchup": "Minnesota Twins @ Chicago Cubs",
  "prob_home": 0.3701,
  "predicted": "Minnesota Twins",
  "winner": "Minnesota Twins",
  "score": "5\u20132",
  "correct": true
 },
 {
  "date": "2026-07-17",
  "matchup": "Baltimore Orioles @ Houston Astros",
  "prob_home": 0.4951,
  "predicted": "Baltimore Orioles",
  "winner": "Baltimore Orioles",
  "score": "3\u20132",
  "correct": true
 },
 {
  "date": "2026-07-17",
  "matchup": "San Diego Padres @ Kansas City Royals",
  "prob_home": 0.4578,
  "predicted": "San Diego Padres",
  "winner": "Kansas City Royals",
  "score": "6\u20137",
  "correct": false
 },
 {
  "date": "2026-07-17",
  "matchup": "Cincinnati Reds @ Colorado Rockies",
  "prob_home": 0.4902,
  "predicted": "Cincinnati Reds",
  "winner": "Cincinnati Reds",
  "score": "7\u20132",
  "correct": true
 },
 {
  "date": "2026-07-17",
  "matchup": "Detroit Tigers @ Los Angeles Angels",
  "prob_home": 0.4783,
  "predicted": "Detroit Tigers",
  "winner": "Detroit Tigers",
  "score": "2\u20131",
  "correct": true
 },
 {
  "date": "2026-07-17",
  "matchup": "Washington Nationals @ Athletics",
  "prob_home": 0.6101,
  "predicted": "Athletics",
  "winner": "Washington Nationals",
  "score": "23\u20134",
  "correct": false
 },
 {
  "date": "2026-07-17",
  "matchup": "St. Louis Cardinals @ Arizona Diamondbacks",
  "prob_home": 0.3701,
  "predicted": "St. Louis Cardinals",
  "winner": "St. Louis Cardinals",
  "score": "5\u20134",
  "correct": true
 },
 {
  "date": "2026-07-17",
  "matchup": "San Francisco Giants @ Seattle Mariners",
  "prob_home": 0.5785,
  "predicted": "Seattle Mariners",
  "winner": "San Francisco Giants",
  "score": "7\u20130",
  "correct": false
 },
 {
  "date": "2026-07-18",
  "matchup": "Pittsburgh Pirates @ Cleveland Guardians",
  "prob_home": 0.4279,
  "predicted": "Pittsburgh Pirates",
  "winner": "Pittsburgh Pirates",
  "score": "7\u20131",
  "correct": true
 },
 {
  "date": "2026-07-18",
  "matchup": "Pittsburgh Pirates @ Cleveland Guardians",
  "prob_home": 0.4878,
  "predicted": "Pittsburgh Pirates",
  "winner": "Cleveland Guardians",
  "score": "3\u20135",
  "correct": false
 },
 {
  "date": "2026-07-18",
  "matchup": "Minnesota Twins @ Chicago Cubs",
  "prob_home": 0.5021,
  "predicted": "Chicago Cubs",
  "winner": "Chicago Cubs",
  "score": "2\u20136",
  "correct": true
 },
 {
  "date": "2026-07-18",
  "matchup": "New York Mets @ Philadelphia Phillies",
  "prob_home": 0.5458,
  "predicted": "Philadelphia Phillies",
  "winner": "Philadelphia Phillies",
  "score": "1\u20136",
  "correct": true
 },
 {
  "date": "2026-07-18",
  "matchup": "Chicago White Sox @ Toronto Blue Jays",
  "prob_home": 0.6554,
  "predicted": "Toronto Blue Jays",
  "winner": "Toronto Blue Jays",
  "score": "0\u20131",
  "correct": true
 },
 {
  "date": "2026-07-18",
  "matchup": "Cincinnati Reds @ Colorado Rockies",
  "prob_home": 0.5957,
  "predicted": "Colorado Rockies",
  "winner": "Colorado Rockies",
  "score": "3\u201310",
  "correct": true
 },
 {
  "date": "2026-07-18",
  "matchup": "Baltimore Orioles @ Houston Astros",
  "prob_home": 0.3934,
  "predicted": "Baltimore Orioles",
  "winner": "Baltimore Orioles",
  "score": "4\u20132",
  "correct": true
 },
 {
  "date": "2026-07-18",
  "matchup": "San Diego Padres @ Kansas City Royals",
  "prob_home": 0.6061,
  "predicted": "Kansas City Royals",
  "winner": "Kansas City Royals",
  "score": "1\u20136",
  "correct": true
 },
 {
  "date": "2026-07-18",
  "matchup": "St. Louis Cardinals @ Arizona Diamondbacks",
  "prob_home": 0.5448,
  "predicted": "Arizona Diamondbacks",
  "winner": "Arizona Diamondbacks",
  "score": "3\u20135",
  "correct": true
 },
 {
  "date": "2026-07-18",
  "matchup": "Tampa Bay Rays @ Boston Red Sox",
  "prob_home": 0.4462,
  "predicted": "Tampa Bay Rays",
  "winner": "Boston Red Sox",
  "score": "6\u20137",
  "correct": false
 },
 {
  "date": "2026-07-18",
  "matchup": "Texas Rangers @ Atlanta Braves",
  "prob_home": 0.7335,
  "predicted": "Atlanta Braves",
  "winner": "Texas Rangers",
  "score": "7\u20136",
  "correct": false
 },
 {
  "date": "2026-07-18",
  "matchup": "Miami Marlins @ Milwaukee Brewers",
  "prob_home": 0.4417,
  "predicted": "Miami Marlins",
  "winner": "Milwaukee Brewers",
  "score": "6\u20138",
  "correct": false
 },
 {
  "date": "2026-07-18",
  "matchup": "San Francisco Giants @ Seattle Mariners",
  "prob_home": 0.5653,
  "predicted": "Seattle Mariners",
  "winner": "Seattle Mariners",
  "score": "3\u20134",
  "correct": true
 },
 {
  "date": "2026-07-18",
  "matchup": "Washington Nationals @ Athletics",
  "prob_home": 0.5573,
  "predicted": "Athletics",
  "winner": "Athletics",
  "score": "1\u201315",
  "correct": true
 },
 {
  "date": "2026-07-18",
  "matchup": "Detroit Tigers @ Los Angeles Angels",
  "prob_home": 0.3592,
  "predicted": "Detroit Tigers",
  "winner": "Detroit Tigers",
  "score": "7\u20130",
  "correct": true
 }
]